restapisdk/__init__.py
restapisdk/api_helper.py
restapisdk/configuration.py
restapisdk/decorators.py
restapisdk/restapisdk_client.py
restapisdk/controllers/__init__.py
restapisdk/controllers/api_controller.py
restapisdk/controllers/base_controller.py
restapisdk/controllers/connection_controller.py
restapisdk/controllers/database_controller.py
restapisdk/controllers/group_controller.py
restapisdk/controllers/metadata_controller.py
restapisdk/controllers/session_controller.py
restapisdk/controllers/user_controller.py
restapisdk/exceptions/__init__.py
restapisdk/exceptions/api_exception.py
restapisdk/exceptions/error_response_exception.py
restapisdk/http/__init__.py
restapisdk/http/http_call_back.py
restapisdk/http/http_client.py
restapisdk/http/http_method_enum.py
restapisdk/http/http_request.py
restapisdk/http/http_response.py
restapisdk/http/requests_client.py
restapisdk/http/auth/__init__.py
restapisdk/http/auth/o_auth_2.py
restapisdk/models/__init__.py
restapisdk/models/access_enum.py
restapisdk/models/access_level_input.py
restapisdk/models/analyst_onboarding_complete_enum.py
restapisdk/models/api_rest_v_2_connection_addtable_request.py
restapisdk/models/api_rest_v_2_connection_create_request.py
restapisdk/models/api_rest_v_2_connection_removetable_request.py
restapisdk/models/api_rest_v_2_connection_search_request.py
restapisdk/models/api_rest_v_2_connection_update_request.py
restapisdk/models/api_rest_v_2_database_table_create_request.py
restapisdk/models/api_rest_v_2_database_table_runquery_request.py
restapisdk/models/api_rest_v_2_group_addgroup_request.py
restapisdk/models/api_rest_v_2_group_addprivilege_request.py
restapisdk/models/api_rest_v_2_group_adduser_request.py
restapisdk/models/api_rest_v_2_group_create_request.py
restapisdk/models/api_rest_v_2_group_removegroup_request.py
restapisdk/models/api_rest_v_2_group_removeprivilege_request.py
restapisdk/models/api_rest_v_2_group_removeuser_request.py
restapisdk/models/api_rest_v_2_group_search_request.py
absarv3testing8-1.1.1.dist-info/LICENSE
absarv3testing8-1.1.1.dist-info/METADATA
absarv3testing8-1.1.1.dist-info/WHEEL
absarv3testing8-1.1.1.dist-info/top_level.txt
absarv3testing8-1.1.1.dist-info/RECORD
